<MetaData>
  <Preset Name="ACT2_Mercy_Arena">
    <DesignParams DisableTeleport="1" />
  </Preset>
  <Preset Name="ACT2_Inner_Sanctum">
    <DesignParams DisableTeleport="1" />
  </Preset>
  <Preset Name="ACT2_VOS2_Event">
    <DesignParams DisableTeleport="1" />
  </Preset>
  <Preset Name="ACT2_Forest_Clearing">
    <DesignParams DisableTeleport="1" />
  </Preset>
  <Preset Name="ACT2_Flesh_City">
    <DesignParams DisableTeleport="1" />
  </Preset>
  <Preset Name="ACT2_BossFight_Lambach">
    <DesignParams DisableTeleport="1" />
  </Preset>
</MetaData>