<MetaData>
  <Preset ID="skillloop_frostcomet">
    <StartLoop>
      <VFX Key="startloop" Name="U_Magic_Sign.Frost.Ice_Meteor_Sign_01" Offset="0,0,0" Direction="0,0,1" Scale="1" InstantKill="0" />
      <Audio Trigger="" />
    </StartLoop>
  </Preset>
  <Preset ID="skillloop_frostcomet_fire">
    <StartLoop>
      <VFX Key="startloop" Name="U_Magic_Sign.Fire.Fire_Meteor_Sign_01" Offset="0,0,0" Direction="0,0,1" Scale="1" InstantKill="0" />
      <Audio Trigger="" />
    </StartLoop>
  </Preset>
  <Preset ID="skillloop_frostcomet_rend">
    <StartLoop>
      <VFX Key="startloop" Name="U_Magic_Sign.Rend.Ice_Meteor_Sign_01" Offset="0,0,0" Direction="0,0,1" Scale="1" InstantKill="0" />
      <Audio Trigger="" />
    </StartLoop>
  </Preset>
  <Preset ID="skillloop_frostcomet_sacred">
    <StartLoop>
      <VFX Key="startloop" Name="U_Magic_Sign.Sacred.Ice_Meteor_Sign_01" Offset="0,0,0" Direction="0,0,1" Scale="1" InstantKill="0" />
      <Audio Trigger="" />
    </StartLoop>
  </Preset>
</MetaData>